cjkstr/__init__.py
cjkstr-0.0.5.dist-info/LICENSE
cjkstr-0.0.5.dist-info/METADATA
cjkstr-0.0.5.dist-info/WHEEL
cjkstr-0.0.5.dist-info/top_level.txt
cjkstr-0.0.5.dist-info/RECORD
