Metadata-Version: 2.1
Name: cjkstr
Version: 0.0.5
Summary: A simple package to processing CJK string
Home-page: https://github.com/codemee/cjkstr
Author: Shin-Wei Hwang
Author-email: meebox@gmail.com
License: UNKNOWN
Platform: UNKNOWN
Classifier: Programming Language :: Python :: 3
Classifier: License :: OSI Approved :: MIT License
Classifier: Operating System :: OS Independent
Requires-Python: >=3.0
